st_card_component_2/__init__.py
st_card_component_2/frontend/build/asset-manifest.json
st_card_component_2/frontend/build/bootstrap.min.css
st_card_component_2/frontend/build/index.html
st_card_component_2/frontend/build/precache-manifest.bd4788e3e9b9488c4e9fe4c4bfeefad8.js
st_card_component_2/frontend/build/service-worker.js
st_card_component_2/frontend/build/static/css/2.ae70d507.chunk.css
st_card_component_2/frontend/build/static/css/2.ae70d507.chunk.css.map
st_card_component_2/frontend/build/static/js/2.347ca8a2.chunk.js
st_card_component_2/frontend/build/static/js/2.347ca8a2.chunk.js.LICENSE.txt
st_card_component_2/frontend/build/static/js/2.347ca8a2.chunk.js.map
st_card_component_2/frontend/build/static/js/main.2e6a0890.chunk.js
st_card_component_2/frontend/build/static/js/main.2e6a0890.chunk.js.map
st_card_component_2/frontend/build/static/js/runtime-main.11ec9aca.js
st_card_component_2/frontend/build/static/js/runtime-main.11ec9aca.js.map
st_card_component_2/frontend/build/static/media/roboto-all-300-normal.130eafc2.woff
st_card_component_2/frontend/build/static/media/roboto-all-400-normal.73f26bf9.woff
st_card_component_2/frontend/build/static/media/roboto-all-500-normal.08926d7a.woff
st_card_component_2/frontend/build/static/media/roboto-all-700-normal.8b2b2aae.woff
st_card_component_2/frontend/build/static/media/roboto-cyrillic-300-normal.4a2f6d13.woff2
st_card_component_2/frontend/build/static/media/roboto-cyrillic-400-normal.ba2c6cb0.woff2
st_card_component_2/frontend/build/static/media/roboto-cyrillic-500-normal.ad72d5d4.woff2
st_card_component_2/frontend/build/static/media/roboto-cyrillic-700-normal.37afd1fe.woff2
st_card_component_2/frontend/build/static/media/roboto-cyrillic-ext-300-normal.607808ee.woff2
st_card_component_2/frontend/build/static/media/roboto-cyrillic-ext-400-normal.2e0b8660.woff2
st_card_component_2/frontend/build/static/media/roboto-cyrillic-ext-500-normal.d697abd3.woff2
st_card_component_2-0.0.1.dist-info/LICENSE
st_card_component_2-0.0.1.dist-info/METADATA
st_card_component_2-0.0.1.dist-info/WHEEL
st_card_component_2-0.0.1.dist-info/top_level.txt
st_card_component_2-0.0.1.dist-info/RECORD
